[
  {
    "shared_id": "000011",
    "emory_courses": [
      "HLTH210",
      "MATH190",
      "MUS220",
      "HLTH100",
      "CS370",
      "MATH250",
      "CS334",
      "CS224",
      "ENGRD101",
      "PE130",
      "ECS101",
      "CS377",
      "CS326",
      "CS170",
      "MATH221",
      "CS171",
      "ENG215",
      "CS253"
    ],
    "incoming_test_courses": ["ECON101", "FREN201", "MATH111", "MATH112Z"],
    "incoming_transfer_courses": []
  },
  {
    "shared_id": "000012",
    "emory_courses": [
      "CS325",
      "ENVS120",
      "MATH190",
      "MATH112",
      "HLTH100",
      "ANT231",
      "QTM110",
      "CS334",
      "CS224",
      "ENGRD101",
      "PE130",
      "ECS101",
      "MATH221",
      "CS171",
      "CS253",
      "CS255"
    ],
    "incoming_test_courses": [],
    "incoming_transfer_courses": []
  },
  {
    "shared_id": "000013",
    "emory_courses": [
      "CHN402W",
      "MATH190",
      "MATH212",
      "MATH112",
      "AFS221",
      "HLTH100",
      "CS370",
      "CS334",
      "CS224",
      "ENGRD101",
      "PE130",
      "ECS101",
      "CS377",
      "CS326",
      "MATH221",
      "CS171",
      "QTM100",
      "CS253",
      "LING342"
    ],
    "incoming_test_courses": ["CS170", "FREN201", "MATH111", "PHYS141"],
    "incoming_transfer_courses": []
  },
  {
    "shared_id": "000014",
    "emory_courses": [
      "LACS270W",
      "CS325",
      "MATH211",
      "MATH190",
      "MATH112",
      "HLTH100",
      "MATH315",
      "CS224",
      "ENGRD101",
      "ENG205",
      "PE130",
      "ECS101",
      "CS377",
      "MATH221",
      "CS171",
      "CS253",
      "HEBR101",
      "CS255"
    ],
    "incoming_test_courses": ["BIOL141", "MATH111", "PHYS141", "RUSS102"],
    "incoming_transfer_courses": []
  },
  {
    "shared_id": "000015",
    "emory_courses": [
      "MATH190",
      "HLTH100",
      "CS370",
      "MATH250",
      "QTM110",
      "MATH315",
      "CS224",
      "ENGRD101",
      "PE130",
      "ECS101",
      "LING101",
      "ENG255W",
      "CS377",
      "CS170",
      "MATH221",
      "CS171",
      "CS253",
      "CS255"
    ],
    "incoming_test_courses": ["MATH111", "MATH112Z", "PHYS141"],
    "incoming_transfer_courses": []
  },
  {
    "shared_id": "000016",
    "emory_courses": [
      "MATH190",
      "MATH112",
      "HLTH100",
      "CS370",
      "MATH250",
      "MATH111",
      "CS224",
      "ENGRD101",
      "ENG205",
      "PE130",
      "ECS101",
      "KRN302",
      "PHYS222",
      "MATH221",
      "CS171",
      "CS253",
      "RUSS270W",
      "CS255"
    ],
    "incoming_test_courses": [],
    "incoming_transfer_courses": []
  },
  {
    "shared_id": "000017",
    "emory_courses": [
      "MATH190",
      "CS329",
      "MATH112",
      "HLTH100",
      "CS350",
      "CS224",
      "ENGRD101",
      "PE130",
      "QTM220",
      "ECS101",
      "CS377",
      "ENVS140",
      "CS170",
      "CS171",
      "ENG356W",
      "CS253",
      "CS255"
    ],
    "incoming_test_courses": ["ARTVIS103", "BIOL141", "MATH111"],
    "incoming_transfer_courses": []
  },
  {
    "shared_id": "000018",
    "emory_courses": [
      "GER218",
      "ECON231",
      "ECS101",
      "PE130",
      "CPLT495BW",
      "MESAS238",
      "MATH190",
      "HIST239",
      "MATH221",
      "CS170",
      "CS171",
      "CS110",
      "HLTH100",
      "HIST221",
      "PHYS116",
      "CS224",
      "CS255"
    ],
    "incoming_test_courses": [
      "ARTVIS103",
      "BIOL141",
      "CHEM150",
      "CHEM150L",
      "ENGRD101",
      "MATH111",
      "PHYS142"
    ],
    "incoming_transfer_courses": []
  },
  {
    "shared_id": "000019",
    "emory_courses": [
      "CS325",
      "MATH211",
      "MESAS190",
      "MATH190",
      "CS329",
      "MATH212",
      "CHEM203",
      "HLTH100",
      "CS370",
      "CS334",
      "CS224",
      "ENGRD101",
      "PE130",
      "ECS101",
      "CS170",
      "MATH221",
      "CS171",
      "CS253"
    ],
    "incoming_test_courses": ["MATH111", "MATH112Z"],
    "incoming_transfer_courses": []
  },
  {
    "shared_id": "000020",
    "emory_courses": [
      "MATH190",
      "ANT203",
      "HLTH100",
      "MATH250",
      "MATH315",
      "PE130",
      "CHEM202",
      "CS170",
      "HIST206W",
      "CS253",
      "CS224",
      "MESAS102",
      "ENGRD101",
      "ECS101",
      "CS377",
      "CS326",
      "MATH221",
      "CS171",
      "CS255"
    ],
    "incoming_test_courses": [
      "ARTHIST101",
      "ECON101",
      "GRK102",
      "MATH111",
      "PHYS141",
      "PHYS142",
      "THEA100"
    ],
    "incoming_transfer_courses": []
  }
]
